{"entity": "WaylonSmithers", "date": "2021/05/22", "tagList": ["riskmanagement", "attentiontodetail", "safetyconsciousness"], "observation": "On May 22nd, 2021, @WaylonSmithers was observed to perform to an excellent standard. This was evidenced by his coordination of a company-wide health and safety audit, which identified several areas for improvement and helped to prevent accidents. His actions show #riskmanagement #attentiontodetail #safetyconsciousness.\n", "observer": "MontgomeryBurns", "lastModified": "2023/04/08 16:46:40"}